stock_info_easy/__init__.py
stock_info_easy/stock_info_easy.py
stock_info_easy/stock_info_easy_draft.py
stock_info_easy-1.4.1.dist-info/LICENSE
stock_info_easy-1.4.1.dist-info/WHEEL
stock_info_easy-1.4.1.dist-info/METADATA
stock_info_easy-1.4.1.dist-info/RECORD
