Metadata-Version: 2.1
Name: stock-info-easy
Version: 1.4.1
Summary: This package provides user-friendly functions to easily navigate stock information of the companies of their interests. The output results include visualization of closing prices and daily returns, stock prediction for the next twenty days, as well as the company information with sectors and PE ratios.
Home-page: https://github.com/shaunahan/Stock_Info_Easy
License: MIT
Author: Shauna Han
Requires-Python: >=3.8,<4.0
Classifier: License :: OSI Approved :: MIT License
Classifier: Programming Language :: Python :: 3
Classifier: Programming Language :: Python :: 3.8
Classifier: Programming Language :: Python :: 3.9
Classifier: Programming Language :: Python :: 3.10
Requires-Dist: pandas (>=1.5.2,<2.0.0)
Project-URL: Repository, https://github.com/shaunahan/Stock_Info_Easy
